rabbithole/__init__.py
rabbithole/asyncio_rabbit_manager.py
rabbithole/asyncio_rabbit_manager_factory.py
rabbithole/constants.py
rabbithole/hole_wrapper.py
rabbithole/rabbit_log_messages.py
rabbithole/rabbit_manager.py
rabbithole/config/__init__.py
rabbithole/config/asyncio_rabbit_config.py
rabbithole/config/config_file_manager.py
rabbithole/config/rabbit_config.py
gh_rabbit_hole-1.6.0.dist-info/LICENSE
gh_rabbit_hole-1.6.0.dist-info/METADATA
gh_rabbit_hole-1.6.0.dist-info/WHEEL
gh_rabbit_hole-1.6.0.dist-info/top_level.txt
gh_rabbit_hole-1.6.0.dist-info/RECORD
