Metadata-Version: 2.1
Name: gh-rabbit-hole
Version: 1.6.0
Summary: Package for communication with RabbitMQ
Home-page: https://github.com/m-ghiani/RABBIT_HOLE
Author: Massimo Ghiani
Author-email: m.ghiani@gmail.com
License: MIT
Project-URL: Documentation, https://github.com/m-ghiani/RABBIT_HOLE/tree/main/rabbit_manager_package/documentation
Classifier: Development Status :: 5 - Production/Stable
Classifier: Intended Audience :: Developers
Classifier: License :: OSI Approved :: MIT License
Classifier: Programming Language :: Python :: 3
Classifier: Programming Language :: Python :: 3.6
Classifier: Programming Language :: Python :: 3.7
Classifier: Programming Language :: Python :: 3.8
Classifier: Programming Language :: Python :: 3.9
Classifier: Programming Language :: Python :: 3.10
Classifier: Programming Language :: Python :: 3.11
Classifier: Programming Language :: Python :: 3.12
Requires-Python: >=3.10
License-File: LICENSE
Requires-Dist: pika >=1.3.2
Requires-Dist: requests >=2.31.0
Requires-Dist: asyncio >=3.4.3
